mjai-0.2.1.dist-info/METADATA
mjai-0.2.1.dist-info/WHEEL
mjai-0.2.1.dist-info/license_files/LICENSE
mjai/elo.py
mjai/game.py
mjai/__init__.py
mjai/matching.py
mjai/engine.py
mjai/http_server/server.py
mjai/player.py
mjai/exceptions.py
mjai/bot/riichibot.py
mjai/bot/rulebase.py
mjai/bot/tools.py
mjai/bot/__init__.py
mjai/bot/consts.py
mjai/bot/base.py
mjai/verify.py
mjai/mlibriichi.cpython-311-darwin.so
mjai-0.2.1.dist-info/RECORD
