Metadata-Version: 2.3
Name: mjai
Version: 0.2.1
Classifier: Programming Language :: Rust
Classifier: Environment :: Console
Classifier: Intended Audience :: Developers
Classifier: License :: OSI Approved :: GNU Affero General Public License v3 or later (AGPLv3+)
Classifier: Programming Language :: Python
Classifier: Programming Language :: Python :: 3.10
Classifier: Programming Language :: Python :: 3.11
Classifier: Programming Language :: Python :: 3.12
Classifier: Programming Language :: Python :: 3 :: Only
Classifier: Topic :: Software Development :: Libraries :: Python Modules
Classifier: Topic :: Games/Entertainment :: Board Games
Requires-Dist: mahjong ~=1.2.0
Requires-Dist: loguru
Requires-Dist: requests
Requires-Dist: pytest ~=8.2.2 ; extra == 'test'
Requires-Dist: mock ; extra == 'test'
Requires-Dist: flake8 ; extra == 'test'
Requires-Dist: black ; extra == 'test'
Requires-Dist: isort ; extra == 'test'
Requires-Dist: pyright ; extra == 'test'
Provides-Extra: test
License-File: LICENSE
Summary: Mahjong game simulator for evaluating submission files on mjai.app
Keywords: mahjong,mjai,game,simulator
Author-email: smly <eown.er+mjai@gmail.com>
Requires-Python: >=3.10
Project-URL: Repository, https://github.com/smly/mjai.app
Project-URL: Docuemntation, https://github.com/smly/mjai.app/blob/main/README.md
